spotrend/__init__.py
spotrend/client.py
spotrend/exceptions.py
spotrend/pytest.ini
spotrend-0.0.2.dist-info/METADATA
spotrend-0.0.2.dist-info/WHEEL
spotrend-0.0.2.dist-info/licenses/LICENSE
spotrend-0.0.2.dist-info/RECORD
