Metadata-Version: 2.1
Name: spotrend
Version: 0.0.2
Summary: Fundament package for Spotify data integration using Spotipy and Spotify API.
Project-URL: Homepage, https://github.com/spotrend/spotrend
Project-URL: Bug Tracker, https://github.com/spotrend/spotrend/issues
Author-email: Mario Sessa <kode.gcloud@gmail.com>
License-File: LICENSE
Classifier: License :: OSI Approved :: MIT License
Classifier: Operating System :: OS Independent
Classifier: Programming Language :: Python :: 3
Requires-Python: >=3.7
